{
  "project_info": {
    "project_number": "1033180178034",
    "project_id": "nucleon-iot",
    "storage_bucket": "nucleon-iot.firebasestorage.app"
  },
  "client": [
    {
      "client_info": {
        "mobilesdk_app_id": "1:1033180178034:android:962536290309f6fb8c84eb",
        "android_client_info": {
          "package_name": "com.nucleon.iot"
        }
      },
      "oauth_client": [],
      "api_key": [
        {
          "current_key": "AIzaSyC8EadC3SQsai5IsC927XYaV-Hcx4iGuak"
        }
      ],
      "services": {
        "appinvite_service": {
          "other_platform_oauth_client": []
        }
      }
    }
  ],
  "configuration_version": "1"
}